finite_state_machine/__init__.py
finite_state_machine/draw_state_diagram.py
finite_state_machine/exceptions.py
finite_state_machine/state_machine.py
finite_state_machine-0.5.0.dist-info/entry_points.txt
finite_state_machine-0.5.0.dist-info/LICENSE
finite_state_machine-0.5.0.dist-info/WHEEL
finite_state_machine-0.5.0.dist-info/METADATA
finite_state_machine-0.5.0.dist-info/RECORD
