Metadata-Version: 1.1
Name: finite-state-machine
Version: 0.5.0
Summary: Lightweight, decorator-based implementation of a Finite State Machine
Home-page: https://github.com/alysivji/finite-state-machine
Author: Aly Sivji
Author-email: alysivji@gmail.com
